jack_connection_manager/ConnectionManager.py
jack_connection_manager/__init__.py
jack_connection_manager/_version.py
jack_connection_manager/jack_connection_manager.py
jack_connection_manager-0.0.10.dist-info/LICENSE
jack_connection_manager-0.0.10.dist-info/METADATA
jack_connection_manager-0.0.10.dist-info/WHEEL
jack_connection_manager-0.0.10.dist-info/entry_points.txt
jack_connection_manager-0.0.10.dist-info/top_level.txt
jack_connection_manager-0.0.10.dist-info/RECORD
