Metadata-Version: 2.1
Name: jack_connection_manager
Version: 0.0.10
Summary: A tool for automatically connecting jack clients with lots of ports
Author-email: Max Weidauer <weidauer@campus.tu-berlin.de>
License: GNU GENERAL PUBLIC LICENSE
Project-URL: Github, https://github.com/tu-studio/jack-connection-manager
Project-URL: Issues, https://github.com/tu-studio/jack-connection-manager/issues
Requires-Python: >=3.10
License-File: LICENSE
Requires-Dist: JACK-Client
Requires-Dist: click
Requires-Dist: pyYAML
Requires-Dist: sdnotify
